AEfunniest/__init__.py
AEfunniest/lib2.py
AEfunniest-0.2.dist-info/METADATA
AEfunniest-0.2.dist-info/WHEEL
AEfunniest-0.2.dist-info/top_level.txt
AEfunniest-0.2.dist-info/RECORD
