Metadata-Version: 2.1
Name: AEfunniest
Version: 0.2
Summary: I am Taiwanese
Home-page: http://github.com/storborg/AEfunniest
Author: Eason Hsieh
Author-email: eason.hsieh@outlook.com
License: MIT
Platform: UNKNOWN
